DataLoader/Base.py
DataLoader/__init__.py
DataLoader/calendarpd.py
DataLoader/config.py
DataLoader/consus.py
DataLoader/daily.py
DataLoader/registor.py
DataLoader/reports.py
DataLoader/status.py
DataLoader/tools.py
DataLoader/utils.py
JTdata-1.5.21.dist-info/LICENSE
JTdata-1.5.21.dist-info/METADATA
JTdata-1.5.21.dist-info/WHEEL
JTdata-1.5.21.dist-info/top_level.txt
JTdata-1.5.21.dist-info/RECORD
