Metadata-Version: 2.1
Name: JTdata
Version: 1.5.21
Summary: data api
Home-page: https://oa.csc.com.cn
Author: wangcc
Author-email: 705190651@qq.com
License: UNKNOWN
Platform: UNKNOWN
